{
  "schemaVersion": 1,
  "generatedAt": "2026-07-22T00:00:00Z",
  "generatorVersion": 1,
  "source": "../../YouNew/Resources/Data/younew-runtime-data.json",
  "sourceMode": "production",
  "sourceSchemaVersion": 1,
  "datasetFingerprint": "15154a987cb41b4677a37543adbecc11ea2bf491c27fceb75fc06ba058973853",
  "sourceOutputChecksum": "0828335a30d266103f06229907dd57203b535ddd9b5858ebfc87fcc6c53cbf08",
  "acceptedReleaseIds": [
    "amsterdam-v0.1.1",
    "cities-v0.1.0"
  ],
  "publicationRules": {
    "datasetMode": "production",
    "entityKinds": [
      "cafe",
      "city",
      "event",
      "governmentService",
      "healthcare",
      "knowledgeTopic",
      "localPartner",
      "museum",
      "park",
      "place",
      "restaurant",
      "transport",
      "university"
    ],
    "releaseStatus": "published",
    "recordLifecycleStatus": "published",
    "recordVerificationStatus": "verified",
    "sourceStatus": "verified_opened"
  },
  "counts": {
    "sourceRecords": 188,
    "acceptedRecords": 188,
    "excludedRecords": 0
  }
}
